{"start":"2016-11-25T13:17:44.063Z","end":"2016-11-25T13:18:21.178Z","capabilities":{"maxInstances":5,"browserName":"chrome"},"host":"127.0.0.1","port":4444,"baseUrl":"https://gmail.com","framework":"mocha","mochaOpts":{"timeout":99999999,"ui":"bdd","compilers":["js:babel-register"],"require":["./test/helpers/common.js"]},"suites":[{"name":"Home Page","duration":25957,"start":"2016-11-25T13:17:53.972Z","end":"2016-11-25T13:18:19.929Z","tests":[{"name":"Should login and display the home page and send a mail to the user","start":"2016-11-25T13:17:53.976Z","end":"2016-11-25T13:18:19.928Z","duration":25952,"state":"fail","errorType":"TypeError","error":"HomePage.composemail.to is not a function","standardError":"TypeError: HomePage.composemail.to is not a function\n    at Context.<anonymous> (D:/SonyChandra/test/specs/LoginLogoutTest.js:17:30)\n    at D:\\SonyChandra\\node_modules\\wdio-sync\\build\\index.js:678:26\n    at Context.executeSync (D:\\SonyChandra\\node_modules\\wdio-sync\\build\\index.js:676:12)\n    at D:\\SonyChandra\\node_modules\\wdio-sync\\build\\index.js:902:34"}],"hooks":[{"start":"2016-11-25T13:17:53.979Z","end":"2016-11-25T13:17:53.980Z","duration":1,"title":"\"before each\" hook","associatedSuite":"Home Page","associatedTest":"Should login and display the home page and send a mail to the user"},{"start":"2016-11-25T13:18:19.929Z","end":"2016-11-25T13:18:19.929Z","duration":0,"title":"\"after each\" hook","associatedSuite":"Home Page","associatedTest":"Should login and display the home page and send a mail to the user"},{"start":"2016-11-25T13:18:19.953Z","end":"2016-11-25T13:18:19.953Z","duration":0,"title":"\"after all\" hook","associatedSuite":"Home Page"}]}],"state":{"passed":0,"failed":1,"skipped":0}}